allensdk/__init__.py
allensdk/deprecated.py
allensdk/api/__init__.py
allensdk/api/api.py
allensdk/api/cloud_cache/__init__.py
allensdk/api/cloud_cache/cloud_cache.py
allensdk/api/cloud_cache/file_attributes.py
allensdk/api/cloud_cache/manifest.py
allensdk/api/cloud_cache/utils.py
allensdk/api/queries/__init__.py
allensdk/api/queries/annotated_section_data_sets_api.py
allensdk/api/queries/biophysical_api.py
allensdk/api/queries/brain_observatory_api.py
allensdk/api/queries/cell_types_api.py
allensdk/api/queries/connected_services.py
allensdk/api/queries/glif_api.py
allensdk/api/queries/grid_data_api.py
allensdk/api/queries/image_download_api.py
allensdk/api/queries/mouse_atlas_api.py
allensdk/api/queries/mouse_connectivity_api.py
allensdk/api/queries/ontologies_api.py
allensdk/api/queries/reference_space_api.py
allensdk/api/queries/rma_api.py
allensdk/api/queries/rma_pager.py
allensdk/api/queries/rma_template.py
allensdk/api/queries/svg_api.py
allensdk/api/queries/synchronization_api.py
allensdk/api/queries/tree_search_api.py
allensdk/api/warehouse_cache/__init__.py
allensdk/api/warehouse_cache/cache.py
allensdk/api/warehouse_cache/caching_utilities.py
allensdk/brain_observatory/__init__.py
allensdk/brain_observatory/argschema_utilities.py
allensdk/brain_observatory/brain_observatory_exceptions.py
allensdk/brain_observatory/brain_observatory_plotting.py
allensdk/brain_observatory/chisquare_categorical.py
allensdk/brain_observatory/circle_plots.py
allensdk/brain_observatory/comparison_utils.py
allensdk/brain_observatory/demixer.py
allensdk/brain_observatory/dff.py
allensdk/brain_observatory/drifting_gratings.py
allensdk/brain_observatory/findlevel.py
allensdk/brain_observatory/locally_sparse_noise.py
allensdk/brain_observatory/natural_movie.py
allensdk/brain_observatory/natural_scenes.py
allensdk/brain_observatory/observatory_plots.py
allensdk/brain_observatory/r_neuropil.py
allensdk/brain_observatory/roi_masks.py
allensdk/brain_observatory/running_speed.py
allensdk-2.16.1.dist-info/LICENSE.txt
allensdk-2.16.1.dist-info/METADATA
allensdk-2.16.1.dist-info/WHEEL
allensdk-2.16.1.dist-info/top_level.txt
allensdk-2.16.1.dist-info/RECORD
